mpa/__init__.py
mpa/builder.py
mpa/registry.py
mpa/stage.py
mpa/version.py
mpa/workflow.py
mpa/cls/__init__.py
mpa/cls/evaluator.py
mpa/cls/explainer.py
mpa/cls/exporter.py
mpa/cls/inferrer.py
mpa/cls/stage.py
mpa/cls/trainer.py
mpa/det/__init__.py
mpa/det/evaluator.py
mpa/det/exporter.py
mpa/det/inferrer.py
mpa/det/stage.py
mpa/det/trainer.py
mpa/modules/__init__.py
mpa/modules/datasets/__init__.py
mpa/modules/datasets/cls_csv_dataset.py
mpa/modules/datasets/cls_csv_incr_dataset.py
mpa/modules/datasets/cls_dir_dataset.py
mpa/modules/datasets/composed_dataloader.py
mpa/modules/datasets/det_csv_dataset.py
mpa/modules/datasets/det_incr_dataset.py
mpa/modules/datasets/multi_cls_dataset.py
mpa/modules/datasets/pseudo_balanced_dataset.py
mpa/modules/datasets/seg_incr_cityscapes_dataset.py
mpa/modules/datasets/seg_incr_voc_dataset.py
mpa/modules/datasets/seg_task_adapt_dataset.py
mpa/modules/datasets/task_adapt_dataset.py
mpa/modules/datasets/pipelines/__init__.py
mpa/modules/datasets/pipelines/torchvision2mmdet.py
mpa/modules/datasets/pipelines/transforms/__init__.py
mpa/modules/datasets/pipelines/transforms/augmix.py
mpa/modules/datasets/pipelines/transforms/ote_transforms.py
mpa/modules/datasets/pipelines/transforms/random_augment.py
mpa/modules/datasets/pipelines/transforms/random_ratio_crop.py
mpa/modules/datasets/samplers/__init__.py
mpa/modules/datasets/samplers/balanced_sampler.py
mpa/modules/datasets/samplers/cls_incr_sampler.py
mpa/modules/datasets/samplers/distributed_sampler.py
mpa/modules/hooks/__init__.py
mpa/modules/hooks/adaptive_training_hooks.py
mpa/modules/hooks/cancel_interface_hook.py
mpa/modules/hooks/checkpoint_hook.py
mpa/modules/hooks/early_stopping_hook.py
mpa/modules/hooks/eval_hook.py
mpa/modules/hooks/fp16_sam_optimizer_hook.py
mpa/modules/hooks/gpu_monitor.py
mpa/modules/hooks/hpo_hook.py
mpa/modules/hooks/ib_loss_hook.py
mpa/modules/hooks/logger_replace_hook.py
mpa/modules/hooks/mem_inspect_hook.py
mpa/modules/hooks/model_ema_hook.py
otxmpa-0.3.0.dist-info/LICENSE
otxmpa-0.3.0.dist-info/METADATA
otxmpa-0.3.0.dist-info/WHEEL
otxmpa-0.3.0.dist-info/top_level.txt
otxmpa-0.3.0.dist-info/RECORD
